splleed/__init__.py
splleed/api.py
splleed/loaders.py
splleed/synthetic.py
splleed/backends/__init__.py
splleed/backends/base.py
splleed/backends/_template/README.md
splleed/backends/_template/__init__.py
splleed/backends/_template/backend.py
splleed/backends/_template/config.py
splleed/backends/tgi/__init__.py
splleed/backends/tgi/backend.py
splleed/backends/tgi/config.py
splleed/backends/vllm/__init__.py
splleed/backends/vllm/backend.py
splleed/backends/vllm/config.py
splleed/config/__init__.py
splleed/config/base.py
splleed/environment/__init__.py
splleed/environment/capture.py
splleed/environment/engine.py
splleed/environment/gpu.py
splleed/environment/system.py
splleed/environment/types.py
splleed/metrics/__init__.py
splleed/metrics/aggregator.py
splleed/metrics/types.py
splleed/reporters/__init__.py
splleed/reporters/console.py
splleed/reporters/csv.py
splleed/reporters/json.py
splleed/runner/__init__.py
splleed/runner/executor.py
splleed/runner/orchestrator.py
splleed/runner/strategies/__init__.py
splleed/runner/strategies/base.py
splleed/runner/strategies/serve.py
splleed/runner/strategies/throughput.py
splleed/stats/__init__.py
splleed/stats/confidence.py
splleed-0.1.0a3.dist-info/METADATA
splleed-0.1.0a3.dist-info/WHEEL
splleed-0.1.0a3.dist-info/licenses/LICENSE
splleed-0.1.0a3.dist-info/RECORD
