Metadata-Version: 2.4
Name: splleed
Version: 0.1.0a3
Summary: LLM inference benchmarking harness with pluggable backends
Project-URL: Homepage, https://github.com/Bradley-Butcher/Splleed
Project-URL: Repository, https://github.com/Bradley-Butcher/Splleed
Project-URL: Issues, https://github.com/Bradley-Butcher/Splleed/issues
Author-email: Bradley Butcher <bradleybutcher@outlook.com>
License: MIT
License-File: LICENSE
Keywords: benchmark,inference,latency,llm,performance,tgi,vllm
Classifier: Development Status :: 3 - Alpha
Classifier: Intended Audience :: Developers
Classifier: Intended Audience :: Science/Research
Classifier: License :: OSI Approved :: MIT License
Classifier: Programming Language :: Python :: 3
Classifier: Programming Language :: Python :: 3.11
Classifier: Programming Language :: Python :: 3.12
Classifier: Topic :: Scientific/Engineering :: Artificial Intelligence
Requires-Python: >=3.11
Requires-Dist: httpx>=0.25
Requires-Dist: numpy<2.3,>=1.24
Requires-Dist: pydantic>=2.0
Requires-Dist: rich>=13.0
Requires-Dist: tqdm>=4.0
Provides-Extra: hf
Requires-Dist: datasets>=2.0; extra == 'hf'
